AIWebSearcher/__init__.py
AIWebSearcher/server.py
AIWebSearcher/FetchPage/__init__.py
AIWebSearcher/FetchPage/fetchWeb.py
AIWebSearcher/WebSearch/__init__.py
AIWebSearcher/WebSearch/baiduSearchTool.py
AIWebSearcher/useAI2Search/SearchAgent.py
AIWebSearcher/useAI2Search/__init__.py
aiwebsearcher-0.1.2.dist-info/METADATA
aiwebsearcher-0.1.2.dist-info/WHEEL
aiwebsearcher-0.1.2.dist-info/entry_points.txt
aiwebsearcher-0.1.2.dist-info/licenses/LICENSE
aiwebsearcher-0.1.2.dist-info/RECORD
