Metadata-Version: 2.4
Name: aiwebsearcher
Version: 0.1.2
Summary: A Model Context Protocol (MCP) server providing AI-powered Baidu search with intelligent reranking and web content extraction
Project-URL: Homepage, https://github.com/Vist233/Web-Searcher
Project-URL: Repository, https://github.com/Vist233/Web-Searcher
Project-URL: Issues, https://github.com/Vist233/Web-Searcher/issues
Author-email: Vist233 <zhangyvjing@outlook.com>
License: MIT License
License-File: LICENSE
Keywords: ai,baidu,llm,mcp,model-context-protocol,search
Classifier: Development Status :: 4 - Beta
Classifier: Intended Audience :: Developers
Classifier: License :: OSI Approved :: MIT License
Classifier: Programming Language :: Python :: 3
Classifier: Programming Language :: Python :: 3.10
Classifier: Programming Language :: Python :: 3.11
Classifier: Programming Language :: Python :: 3.12
Classifier: Topic :: Internet :: WWW/HTTP :: Dynamic Content
Classifier: Topic :: Software Development :: Libraries :: Python Modules
Requires-Python: >=3.10
Requires-Dist: agno>=0.1.0
Requires-Dist: baidusearch>=1.0.0
Requires-Dist: beautifulsoup4>=4.12.0
Requires-Dist: fastmcp>=0.1.0
Requires-Dist: lxml>=4.9.0
Requires-Dist: openai>=2.1.0
Requires-Dist: pycountry>=22.0.0
Requires-Dist: pydantic>=2.0.0
Requires-Dist: requests>=2.31.0
Requires-Dist: trafilatura>=1.6.0
Provides-Extra: dev
Requires-Dist: black>=23.0.0; extra == 'dev'
Requires-Dist: pytest-asyncio>=0.21.0; extra == 'dev'
Requires-Dist: pytest>=7.0.0; extra == 'dev'
Requires-Dist: ruff>=0.1.0; extra == 'dev'
